{"inkVersion":21,"root":[["^Ini.... ","#","^speaker:Dewa ","/#","#","^expression:A_Dewa_Speak","/#","\n","^Ini bukan kelas 302-A ","#","^speaker:Dewa ","/#","#","^expression:A_Dewa_Speak","/#","\n","^Dimana ini? ","#","^speaker:Dewa ","/#","#","^expression:A_Dewa_Speak","/#","\n","^Kenapa aku seperti berada diluar ruangan padahal aku masuk ke kelas 302-A? ","#","^speaker:Dewa ","/#","#","^expression:A_Dewa_Speak","/#","\n","^Dan lagi.... ","#","^speaker:Dewa ","/#","#","^expression:A_Dewa_Speak","/#","\n","^Kenapa disini seperrti sedang kehilangan warna? ","#","^speaker:Dewa ","/#","#","^expression:A_Dewa_Speak","/#","\n","^... ","#","^speaker:Dewa","/#","\n","^Aku harus tetap fokus ","#","^speaker:Dewa ","/#","#","^expression:A_Dewa_Speak","/#","\n","^Huhhh??? ","#","^speaker:Dewa ","/#","#","^expression:A_Dewa_Bingung","/#","\n","^Itu kan? ","#","^speaker:Dewa ","/#","#","^expression:A_Dewa_Speak","/#","\n","^Ratna!!!! ","#","^speaker:Dewa ","/#","#","^expression:A_Dewa_Panik","/#","\n","^ku harus menolong dia... ","#","^speaker:Dewa ","/#","#","^expression:A_Dewa_Speak","/#","\n","end",["done",{"#f":5,"#n":"g-0"}],null],"done",{"#f":1}],"listDefs":{}}