{"inkVersion":21,"root":[["^Astaghfirullahaladzim ","#","^speaker:Pak Ustad ","/#","#","^expression:A_Pak_Ustad_Speak","/#","\n","^Waffa!!! ","#","^speaker:Pak Ustad ","/#","#","^expression:A_Pak_Ustad_Speak ","/#","#","^Emoji:A_Emoji_Angry","/#","\n","^Bikin saya terkejut aja ","#","^speaker:Pak Ustad ","/#","#","^expression:A_Pak_Ustad_Speak","/#","\n","^Ma-maaf pak ustadz ","#","^speaker:Waffa Kecil ","/#","#","^expression:A_Waffa_Child_Speak","/#","\n","^Kami sedang buru-buru ","#","^speaker:Waffa Kecil ","/#","#","^expression:A_Waffa_Child_Speak","/#","\n","^Buru-buru kemana? ","#","^speaker:Pak Ustad ","/#","#","^expression:A_Pak_Ustad_Speak","/#","\n","^Dan ini siapa? ","#","^speaker:Pak Ustad ","/#","#","^expression:A_Pak_Ustad_Speak","/#","\n","^Tidak biasa kamu pergi dengan orang asing ","#","^speaker:Pak Ustad ","/#","#","^expression:A_Pak_Ustad_Speak","/#","\n","^... ","#","^speaker:Waffa Kecil ","/#","#","^expression:A_Waffa_Child_Speak","/#","\n","^Jadi kalian disini mau apa? ","#","^speaker:Pak Ustad ","/#","#","^expression:A_Pak_Ustad_Speak","/#","\n","^Kami sedang mencari air pak ","#","^speaker:Waffa Kecil ","/#","#","^expression:A_Waffa_Child_Speak","/#","\n","^Kami juga sedang buru-buru karena ada orang yang membutuhkan air itu ","#","^speaker:Waffa Kecil ","/#","#","^expression:A_Waffa_Child_Speak","/#","\n","^Kalau begitu kalian bisa ambil gelas yang ada di dekat tempat wudhu ","#","^speaker:Pak Ustad ","/#","#","^expression:A_Pak_Ustad_Speak","/#","\n","^Lalu ambil saja air dari keran yang ada disana ","#","^speaker:Pak Ustad ","/#","#","^expression:A_Pak_Ustad_Speak","/#","\n","^Dengan begitu kalian bisa dapat air dan ada tempat untuk membawa airnya ","#","^speaker:Pak Ustad ","/#","#","^expression:A_Pak_Ustad_Speak","/#","\n","^Te-terimakasih pak ustadz ","#","^speaker:Waffa Kecil ","/#","#","^expression:A_Waffa_Child_Speak","/#","\n","^Ayo kak Dewa kita ambil air disitu ","#","^speaker:Waffa Kecil ","/#","#","^expression:A_Waffa_Child_Speak","/#","\n","^O-oke ","#","^speaker:Dewa ","/#","#","^expression:A_Dewa_Speak","/#","\n","end",["done",{"#f":5,"#n":"g-0"}],null],"done",{"#f":1}],"listDefs":{}}